hivemindutil/__init__.py
hivemindutil/boundingbox.py
hivemindutil/exceptions.py
hivemindutil/formatters.py
hivemindutil/help.txt
hivemindutil/hm.py
hivemind_util-0.1b44.dist-info/LICENSE
hivemind_util-0.1b44.dist-info/METADATA
hivemind_util-0.1b44.dist-info/WHEEL
hivemind_util-0.1b44.dist-info/top_level.txt
hivemind_util-0.1b44.dist-info/RECORD
