Metadata-Version: 2.1
Name: hivemind-util
Version: 0.1b44
Summary: A simple wrapper for the Hivemind API
Home-page: https://bitbucket.org/hvmd/hivemind.utility
Author: Hivemind
Author-email: support@hvmd.io
License: UNKNOWN
Download-URL: https://bitbucket.org/hvmd/hivemind.utility/get/master.tar.gz
Platform: UNKNOWN
License-File: LICENSE
Requires-Dist: requests
Requires-Dist: pandas (>=0.23.4)
